{
  "consignor": {
    "name": "CDR AYUSH KUMAR",
    "address": "P 29/6 NDV HADDO",
    "address2": "SRI VIJAYA PURAM ",
    "address3": "744102"
  },
  "consignee": {
    "name": "CDR AYUSH KUMAR ",
    "address": "NAVAL BASE KOCHI",
    "address2": "KERALA",
    "address3": "682004"
  },
  "riskDetails": {
    "notInsured": true,
    "insured": false,
    "insuredDetails": {
      "company": "",
      "policy": "",
      "date": "",
      "insuredAmount": "",
      "risk": ""
    }
  },
  "goodsDetails": {
    "gcNumber": "1930  ",
    "gcDate": "18-02-2025",
    "origin": "SRI VIJAYA PURAM ",
    "destination": "KOCHI",
    "contact": "9167303629"
  },
  "freightDetails": {
    "locations": [
      {
        "from": "SRI VIJAYA PURAM ",
        "to": "CHENNAI ",
        "amount": "270000"
      },
      {
        "from": "CHENNAI ",
        "to": "KOCHI",
        "amount": "9000"
      },
      {
        "from": "",
        "to": "",
        "amount": ""
      }
    ]
  },
  "additionalCharges": {
    "loadingCharges": "INCLUDED",
    "insuranceCharges": "NO",
    "gstCharges": "13950.00",
    "gcCharges": "NONE",
    "gstPercentage": "5"
  },
  "grandTotal": "292950.00",
  "gstPaidBy": {
    "consignor": false,
    "consignee": false,
    "exempted": false,
    "transporter": true
  },
  "description": {
    "noOfPackages": "",
    "twoWheelerNo": "NO ",
    "carNo": "KL43J5616",
    "actualWeight": "",
    "chargedWeight": "",
    "cbm": "",
    "goodsValue": "",
    "truckNo": "DD01U9496"
  },
  "created_at": "2025-03-06T04:22:52.717Z"
}